FlowOpt/__init__.py
FlowOpt/flow_operation.py
FlowOpt/resource/__init__.py
FlowOpt/resource/icons/__init__.py
FlowOpt/resource/icons/chrome_icon.png
FlowOpt/resource/icons/terminal_input_password.png
FlowOpt/resource/icons/vim_insert_end.png
FlowOpt/tools/__init__.py
FlowOpt/tools/file_lock.py
FlowOpt/tools/sqlite_models.py
FlowOpt/tools/time_format.py
test_files/__init__.py
flowopt-0.1.2.dist-info/LICENSE
flowopt-0.1.2.dist-info/METADATA
flowopt-0.1.2.dist-info/WHEEL
flowopt-0.1.2.dist-info/entry_points.txt
flowopt-0.1.2.dist-info/top_level.txt
flowopt-0.1.2.dist-info/RECORD
